LICENSE
MANIFEST.in
README.rst
requirements.txt
setup.py
lib/topology_lib_vtysh/__init__.py
lib/topology_lib_vtysh/library.py
lib/topology_lib_vtysh/parser.py
lib/topology_lib_vtysh.egg-info/PKG-INFO
lib/topology_lib_vtysh.egg-info/SOURCES.txt
lib/topology_lib_vtysh.egg-info/dependency_links.txt
lib/topology_lib_vtysh.egg-info/entry_points.txt
lib/topology_lib_vtysh.egg-info/pbr.json
lib/topology_lib_vtysh.egg-info/requires.txt
lib/topology_lib_vtysh.egg-info/top_level.txt