Metadata-Version: 1.1
Name: topology-lib-vtysh
Version: 0.1.0
Summary: Vtysh Communication Library for Topology
Home-page: https://github-sc-p.corp.hp.com/hpe-networking/topology_lib_vtysh
Author: Hewlett Packard Enterprise Development LP
Author-email: asicapi@hp.com
License: UNKNOWN
Keywords: topology_lib_vtysh
Platform: UNKNOWN
Classifier: Development Status :: 3 - Alpha
Classifier: Intended Audience :: Developers
Classifier: License :: OSI Approved :: Apache Software License
Classifier: Natural Language :: English
Classifier: Operating System :: POSIX :: Linux
Classifier: Programming Language :: Python :: 2
Classifier: Programming Language :: Python :: 2.7
Classifier: Programming Language :: Python :: 3
Classifier: Programming Language :: Python :: 3.4
